flask_censor/__init__.py
flask_censor/logic.py
flask_censor/data/wordlist.txt
flask_censor-0.1.dist-info/LICENSE
flask_censor-0.1.dist-info/METADATA
flask_censor-0.1.dist-info/WHEEL
flask_censor-0.1.dist-info/top_level.txt
flask_censor-0.1.dist-info/RECORD
