Metadata-Version: 2.1
Name: flask-censor
Version: 0.1
Summary: A profanity censor with hooks for Flask and Jinja2
Home-page: https://github.com/Laukei/flask-censor
Author: Robert Heath
Author-email: rob@robheath.me.uk
License: UNKNOWN
Platform: UNKNOWN
Classifier: Programming Language :: Python :: 3
Classifier: License :: OSI Approved :: MIT License
Classifier: Operating System :: OS Independent
Classifier: Development Status :: 3 - Alpha
